[
  {
    "@context": "https://imi.go.jp/ns/core/context.jsonld",
    "@type": "場所型",
    "@id": "https://geonames.jp/resource/愛知県刈谷市井ケ谷町西石根",
    "表記": "愛知県刈谷市井ケ谷町西石根",
    "住所": {
      "@type": "住所型",
      "都道府県": "愛知県",
      "市区町村": "刈谷市",
      "町名": "井ケ谷町西石根"
    },
    "参照": {
      "@type": "参照型",
      "種別": "メッシュコード",
      "参照先": [
        "http://data.e-stat.go.jp/lod/gridCode/G2052374074",
        "http://data.e-stat.go.jp/lod/gridCode/G2052374064"
      ]
    },
    "画像": [
      "https://cyberjapandata.gsi.go.jp/xyz/std/18/230875/103782.png",
      "https://cyberjapandata.gsi.go.jp/xyz/std/18/230872/103782.png",
      "https://cyberjapandata.gsi.go.jp/xyz/std/18/230876/103781.png",
      "https://cyberjapandata.gsi.go.jp/xyz/std/18/230876/103780.png",
      "https://cyberjapandata.gsi.go.jp/xyz/std/18/230873/103779.png",
      "https://cyberjapandata.gsi.go.jp/xyz/std/18/230873/103782.png",
      "https://cyberjapandata.gsi.go.jp/xyz/std/18/230875/103779.png",
      "https://cyberjapandata.gsi.go.jp/xyz/std/18/230875/103781.png"
    ]
  },
  {
    "@context": "https://geonames.jp/context.jsonld",
    "@id": "https://geonames.jp/resource/愛知県刈谷市井ケ谷町西石根",
    "@type": "Feature",
    "isDefinedBy": "https://indigo-lab.github.io/geonamesjp/愛知県/刈谷市/井ケ谷町西石根.json",
    "name": "井ケ谷町西石根",
    "alternateName": [
      "井ヶ谷町西石根"
    ],
    "parentFeature": "https://geonames.jp/resource/愛知県刈谷市"
  }
]
