[
  {
    "@context": "https://imi.go.jp/ns/core/context.jsonld",
    "@type": "場所型",
    "@id": "https://geonames.jp/resource/岡山県岡山市内尾",
    "表記": "岡山県岡山市内尾",
    "住所": {
      "@type": "住所型",
      "都道府県": "岡山県",
      "市区町村": "岡山市",
      "町名": "内尾"
    },
    "参照": {
      "@type": "参照型",
      "種別": "メッシュコード",
      "参照先": [
        "http://data.e-stat.go.jp/lod/gridCode/G2051337609",
        "http://data.e-stat.go.jp/lod/gridCode/G2051337617",
        "http://data.e-stat.go.jp/lod/gridCode/G2051337618",
        "http://data.e-stat.go.jp/lod/gridCode/G2051337619",
        "http://data.e-stat.go.jp/lod/gridCode/G2051337627",
        "http://data.e-stat.go.jp/lod/gridCode/G2051337628",
        "http://data.e-stat.go.jp/lod/gridCode/G2051337629"
      ]
    },
    "画像": [
      "https://cyberjapandata.gsi.go.jp/xyz/std/18/228531/104191.png",
      "https://cyberjapandata.gsi.go.jp/xyz/std/18/228533/104191.png",
      "https://cyberjapandata.gsi.go.jp/xyz/std/18/228532/104190.png",
      "https://cyberjapandata.gsi.go.jp/xyz/std/18/228531/104189.png",
      "https://cyberjapandata.gsi.go.jp/xyz/std/18/228541/104190.png",
      "https://cyberjapandata.gsi.go.jp/xyz/std/18/228535/104191.png",
      "https://cyberjapandata.gsi.go.jp/xyz/std/18/228535/104190.png",
      "https://cyberjapandata.gsi.go.jp/xyz/std/18/228533/104188.png",
      "https://cyberjapandata.gsi.go.jp/xyz/std/18/228546/104191.png",
      "https://cyberjapandata.gsi.go.jp/xyz/std/18/228536/104192.png",
      "https://cyberjapandata.gsi.go.jp/xyz/std/18/228538/104192.png",
      "https://cyberjapandata.gsi.go.jp/xyz/std/18/228537/104191.png",
      "https://cyberjapandata.gsi.go.jp/xyz/std/18/228536/104189.png",
      "https://cyberjapandata.gsi.go.jp/xyz/std/18/228534/104187.png",
      "https://cyberjapandata.gsi.go.jp/xyz/std/18/228535/104187.png",
      "https://cyberjapandata.gsi.go.jp/xyz/std/18/228537/104188.png",
      "https://cyberjapandata.gsi.go.jp/xyz/std/18/228536/104186.png",
      "https://cyberjapandata.gsi.go.jp/xyz/std/18/228539/104192.png",
      "https://cyberjapandata.gsi.go.jp/xyz/std/18/228539/104191.png",
      "https://cyberjapandata.gsi.go.jp/xyz/std/18/228540/104192.png",
      "https://cyberjapandata.gsi.go.jp/xyz/std/18/228540/104188.png",
      "https://cyberjapandata.gsi.go.jp/xyz/std/18/228540/104185.png",
      "https://cyberjapandata.gsi.go.jp/xyz/std/18/228542/104189.png",
      "https://cyberjapandata.gsi.go.jp/xyz/std/18/228542/104188.png",
      "https://cyberjapandata.gsi.go.jp/xyz/std/18/228541/104186.png",
      "https://cyberjapandata.gsi.go.jp/xyz/std/18/228543/104187.png",
      "https://cyberjapandata.gsi.go.jp/xyz/std/18/228545/104184.png",
      "https://cyberjapandata.gsi.go.jp/xyz/std/18/228544/104187.png",
      "https://cyberjapandata.gsi.go.jp/xyz/std/18/228544/104186.png",
      "https://cyberjapandata.gsi.go.jp/xyz/std/18/228542/104184.png",
      "https://cyberjapandata.gsi.go.jp/xyz/std/18/228546/104182.png",
      "https://cyberjapandata.gsi.go.jp/xyz/std/18/228544/104183.png",
      "https://cyberjapandata.gsi.go.jp/xyz/std/18/228545/104183.png",
      "https://cyberjapandata.gsi.go.jp/xyz/std/18/228545/104182.png",
      "https://cyberjapandata.gsi.go.jp/xyz/std/18/228547/104182.png",
      "https://cyberjapandata.gsi.go.jp/xyz/std/18/228548/104186.png",
      "https://cyberjapandata.gsi.go.jp/xyz/std/18/228548/104185.png",
      "https://cyberjapandata.gsi.go.jp/xyz/std/18/228547/104187.png",
      "https://cyberjapandata.gsi.go.jp/xyz/std/18/228547/104186.png",
      "https://cyberjapandata.gsi.go.jp/xyz/std/18/228546/104188.png",
      "https://cyberjapandata.gsi.go.jp/xyz/std/18/228547/104189.png",
      "https://cyberjapandata.gsi.go.jp/xyz/std/18/228548/104188.png",
      "https://cyberjapandata.gsi.go.jp/xyz/std/18/228544/104189.png",
      "https://cyberjapandata.gsi.go.jp/xyz/std/18/228543/104191.png",
      "https://cyberjapandata.gsi.go.jp/xyz/std/18/228543/104193.png",
      "https://cyberjapandata.gsi.go.jp/xyz/std/18/228542/104191.png",
      "https://cyberjapandata.gsi.go.jp/xyz/std/18/228542/104192.png",
      "https://cyberjapandata.gsi.go.jp/xyz/std/18/228541/104193.png",
      "https://cyberjapandata.gsi.go.jp/xyz/std/18/228540/104193.png",
      "https://cyberjapandata.gsi.go.jp/xyz/std/18/228545/104194.png",
      "https://cyberjapandata.gsi.go.jp/xyz/std/18/228545/104192.png",
      "https://cyberjapandata.gsi.go.jp/xyz/std/18/228547/104195.png",
      "https://cyberjapandata.gsi.go.jp/xyz/std/18/228545/104196.png",
      "https://cyberjapandata.gsi.go.jp/xyz/std/18/228547/104193.png",
      "https://cyberjapandata.gsi.go.jp/xyz/std/18/228546/104192.png",
      "https://cyberjapandata.gsi.go.jp/xyz/std/18/228548/104192.png",
      "https://cyberjapandata.gsi.go.jp/xyz/std/18/228549/104190.png",
      "https://cyberjapandata.gsi.go.jp/xyz/std/18/228552/104199.png",
      "https://cyberjapandata.gsi.go.jp/xyz/std/18/228548/104196.png",
      "https://cyberjapandata.gsi.go.jp/xyz/std/18/228550/104193.png",
      "https://cyberjapandata.gsi.go.jp/xyz/std/18/228552/104196.png",
      "https://cyberjapandata.gsi.go.jp/xyz/std/18/228553/104195.png",
      "https://cyberjapandata.gsi.go.jp/xyz/std/18/228548/104197.png",
      "https://cyberjapandata.gsi.go.jp/xyz/std/18/228549/104195.png",
      "https://cyberjapandata.gsi.go.jp/xyz/std/18/228550/104197.png",
      "https://cyberjapandata.gsi.go.jp/xyz/std/18/228552/104195.png",
      "https://cyberjapandata.gsi.go.jp/xyz/std/18/228552/104194.png",
      "https://cyberjapandata.gsi.go.jp/xyz/std/18/228551/104197.png",
      "https://cyberjapandata.gsi.go.jp/xyz/std/18/228532/104191.png",
      "https://cyberjapandata.gsi.go.jp/xyz/std/18/228530/104189.png",
      "https://cyberjapandata.gsi.go.jp/xyz/std/18/228532/104189.png",
      "https://cyberjapandata.gsi.go.jp/xyz/std/18/228533/104189.png",
      "https://cyberjapandata.gsi.go.jp/xyz/std/18/228532/104188.png",
      "https://cyberjapandata.gsi.go.jp/xyz/std/18/228542/104185.png",
      "https://cyberjapandata.gsi.go.jp/xyz/std/18/228543/104189.png",
      "https://cyberjapandata.gsi.go.jp/xyz/std/18/228538/104191.png",
      "https://cyberjapandata.gsi.go.jp/xyz/std/18/228536/104188.png",
      "https://cyberjapandata.gsi.go.jp/xyz/std/18/228537/104189.png",
      "https://cyberjapandata.gsi.go.jp/xyz/std/18/228537/104187.png",
      "https://cyberjapandata.gsi.go.jp/xyz/std/18/228536/104187.png",
      "https://cyberjapandata.gsi.go.jp/xyz/std/18/228537/104185.png",
      "https://cyberjapandata.gsi.go.jp/xyz/std/18/228538/104187.png",
      "https://cyberjapandata.gsi.go.jp/xyz/std/18/228538/104188.png",
      "https://cyberjapandata.gsi.go.jp/xyz/std/18/228539/104189.png",
      "https://cyberjapandata.gsi.go.jp/xyz/std/18/228539/104188.png",
      "https://cyberjapandata.gsi.go.jp/xyz/std/18/228539/104187.png",
      "https://cyberjapandata.gsi.go.jp/xyz/std/18/228541/104189.png",
      "https://cyberjapandata.gsi.go.jp/xyz/std/18/228541/104187.png",
      "https://cyberjapandata.gsi.go.jp/xyz/std/18/228549/104186.png",
      "https://cyberjapandata.gsi.go.jp/xyz/std/18/228535/104186.png",
      "https://cyberjapandata.gsi.go.jp/xyz/std/18/228551/104199.png",
      "https://cyberjapandata.gsi.go.jp/xyz/std/18/228538/104190.png"
    ]
  },
  {
    "@context": "https://geonames.jp/context.jsonld",
    "@id": "https://geonames.jp/resource/岡山県岡山市内尾",
    "@type": "Feature",
    "isDefinedBy": "https://indigo-lab.github.io/geonamesjp/岡山県/岡山市/内尾.json",
    "name": "内尾",
    "alternateName": [],
    "parentFeature": "https://geonames.jp/resource/岡山県岡山市"
  }
]
