[
  {
    "@context": "https://imi.go.jp/ns/core/context.jsonld",
    "@type": "場所型",
    "@id": "https://geonames.jp/resource/岐阜県岐阜市折立",
    "表記": "岐阜県岐阜市折立",
    "住所": {
      "@type": "住所型",
      "都道府県": "岐阜県",
      "市区町村": "岐阜市",
      "町名": "折立",
      "住所コード": [
        "http://data.e-stat.go.jp/lod/smallArea/g00200521/2015/S212015470"
      ]
    },
    "参照": {
      "@type": "参照型",
      "種別": "メッシュコード",
      "参照先": [
        "http://data.e-stat.go.jp/lod/gridCode/G2053361548",
        "http://data.e-stat.go.jp/lod/gridCode/G2053361549",
        "http://data.e-stat.go.jp/lod/gridCode/G2053361558"
      ]
    },
    "画像": [
      "https://cyberjapandata.gsi.go.jp/xyz/std/18/230635/103423.png",
      "https://cyberjapandata.gsi.go.jp/xyz/std/18/230634/103423.png",
      "https://cyberjapandata.gsi.go.jp/xyz/std/18/230635/103424.png",
      "https://cyberjapandata.gsi.go.jp/xyz/std/18/230634/103424.png",
      "https://cyberjapandata.gsi.go.jp/xyz/std/18/230634/103425.png",
      "https://cyberjapandata.gsi.go.jp/xyz/std/18/230633/103425.png",
      "https://cyberjapandata.gsi.go.jp/xyz/std/18/230635/103433.png",
      "https://cyberjapandata.gsi.go.jp/xyz/std/18/230635/103425.png",
      "https://cyberjapandata.gsi.go.jp/xyz/std/18/230636/103425.png",
      "https://cyberjapandata.gsi.go.jp/xyz/std/18/230636/103423.png",
      "https://cyberjapandata.gsi.go.jp/xyz/std/18/230637/103423.png",
      "https://cyberjapandata.gsi.go.jp/xyz/std/18/230636/103424.png",
      "https://cyberjapandata.gsi.go.jp/xyz/std/18/230637/103426.png",
      "https://cyberjapandata.gsi.go.jp/xyz/std/18/230637/103425.png",
      "https://cyberjapandata.gsi.go.jp/xyz/std/18/230638/103426.png",
      "https://cyberjapandata.gsi.go.jp/xyz/std/18/230639/103426.png",
      "https://cyberjapandata.gsi.go.jp/xyz/std/18/230640/103426.png",
      "https://cyberjapandata.gsi.go.jp/xyz/std/18/230640/103427.png",
      "https://cyberjapandata.gsi.go.jp/xyz/std/18/230641/103427.png",
      "https://cyberjapandata.gsi.go.jp/xyz/std/18/230641/103428.png",
      "https://cyberjapandata.gsi.go.jp/xyz/std/18/230642/103428.png",
      "https://cyberjapandata.gsi.go.jp/xyz/std/18/230640/103429.png",
      "https://cyberjapandata.gsi.go.jp/xyz/std/18/230641/103429.png",
      "https://cyberjapandata.gsi.go.jp/xyz/std/18/230640/103430.png",
      "https://cyberjapandata.gsi.go.jp/xyz/std/18/230641/103430.png",
      "https://cyberjapandata.gsi.go.jp/xyz/std/18/230639/103429.png",
      "https://cyberjapandata.gsi.go.jp/xyz/std/18/230638/103429.png",
      "https://cyberjapandata.gsi.go.jp/xyz/std/18/230638/103430.png",
      "https://cyberjapandata.gsi.go.jp/xyz/std/18/230638/103431.png",
      "https://cyberjapandata.gsi.go.jp/xyz/std/18/230637/103431.png",
      "https://cyberjapandata.gsi.go.jp/xyz/std/18/230637/103432.png",
      "https://cyberjapandata.gsi.go.jp/xyz/std/18/230637/103430.png",
      "https://cyberjapandata.gsi.go.jp/xyz/std/18/230637/103429.png",
      "https://cyberjapandata.gsi.go.jp/xyz/std/18/230638/103428.png",
      "https://cyberjapandata.gsi.go.jp/xyz/std/18/230639/103428.png",
      "https://cyberjapandata.gsi.go.jp/xyz/std/18/230640/103428.png",
      "https://cyberjapandata.gsi.go.jp/xyz/std/18/230639/103427.png",
      "https://cyberjapandata.gsi.go.jp/xyz/std/18/230638/103427.png",
      "https://cyberjapandata.gsi.go.jp/xyz/std/18/230637/103428.png",
      "https://cyberjapandata.gsi.go.jp/xyz/std/18/230637/103427.png",
      "https://cyberjapandata.gsi.go.jp/xyz/std/18/230636/103426.png",
      "https://cyberjapandata.gsi.go.jp/xyz/std/18/230635/103426.png",
      "https://cyberjapandata.gsi.go.jp/xyz/std/18/230634/103426.png",
      "https://cyberjapandata.gsi.go.jp/xyz/std/18/230634/103427.png",
      "https://cyberjapandata.gsi.go.jp/xyz/std/18/230635/103427.png",
      "https://cyberjapandata.gsi.go.jp/xyz/std/18/230635/103428.png",
      "https://cyberjapandata.gsi.go.jp/xyz/std/18/230635/103429.png",
      "https://cyberjapandata.gsi.go.jp/xyz/std/18/230635/103430.png",
      "https://cyberjapandata.gsi.go.jp/xyz/std/18/230635/103431.png",
      "https://cyberjapandata.gsi.go.jp/xyz/std/18/230636/103431.png",
      "https://cyberjapandata.gsi.go.jp/xyz/std/18/230636/103432.png",
      "https://cyberjapandata.gsi.go.jp/xyz/std/18/230635/103432.png",
      "https://cyberjapandata.gsi.go.jp/xyz/std/18/230634/103432.png",
      "https://cyberjapandata.gsi.go.jp/xyz/std/18/230633/103432.png",
      "https://cyberjapandata.gsi.go.jp/xyz/std/18/230637/103424.png",
      "https://cyberjapandata.gsi.go.jp/xyz/std/18/230634/103422.png",
      "https://cyberjapandata.gsi.go.jp/xyz/std/18/230636/103422.png",
      "https://cyberjapandata.gsi.go.jp/xyz/std/18/230638/103424.png",
      "https://cyberjapandata.gsi.go.jp/xyz/std/18/230639/103425.png",
      "https://cyberjapandata.gsi.go.jp/xyz/std/18/230634/103429.png",
      "https://cyberjapandata.gsi.go.jp/xyz/std/18/230634/103428.png"
    ]
  },
  {
    "@context": "https://geonames.jp/context.jsonld",
    "@id": "https://geonames.jp/resource/岐阜県岐阜市折立",
    "@type": "Feature",
    "isDefinedBy": "https://indigo-lab.github.io/geonamesjp/岐阜県/岐阜市/折立.json",
    "name": "折立",
    "alternateName": [],
    "parentFeature": "https://geonames.jp/resource/岐阜県岐阜市"
  }
]
