[
  {
    "@context": "https://imi.go.jp/ns/core/context.jsonld",
    "@type": "場所型",
    "@id": "https://geonames.jp/resource/新潟県佐渡郡畑野町猿八",
    "表記": "新潟県佐渡郡畑野町猿八",
    "住所": {
      "@type": "住所型",
      "都道府県": "新潟県",
      "郡": "佐渡郡",
      "市区町村": "畑野町",
      "町名": "猿八"
    },
    "参照": {
      "@type": "参照型",
      "種別": "メッシュコード",
      "参照先": [
        "http://data.e-stat.go.jp/lod/gridCode/G2056387322",
        "http://data.e-stat.go.jp/lod/gridCode/G2056387332",
        "http://data.e-stat.go.jp/lod/gridCode/G2056387333"
      ]
    },
    "画像": [
      "https://cyberjapandata.gsi.go.jp/xyz/std/18/231860/101162.png",
      "https://cyberjapandata.gsi.go.jp/xyz/std/18/231855/101164.png",
      "https://cyberjapandata.gsi.go.jp/xyz/std/18/231865/101168.png",
      "https://cyberjapandata.gsi.go.jp/xyz/std/18/231864/101163.png",
      "https://cyberjapandata.gsi.go.jp/xyz/std/18/231859/101171.png"
    ]
  },
  {
    "@context": "https://geonames.jp/context.jsonld",
    "@id": "https://geonames.jp/resource/新潟県佐渡郡畑野町猿八",
    "@type": "Feature",
    "isDefinedBy": "https://indigo-lab.github.io/geonamesjp/新潟県/佐渡郡/畑野町/猿八.json",
    "name": "猿八",
    "alternateName": [],
    "parentFeature": "https://geonames.jp/resource/新潟県佐渡郡畑野町"
  }
]
