[
  {
    "@context": "https://imi.go.jp/ns/core/context.jsonld",
    "@type": "場所型",
    "@id": "https://geonames.jp/resource/三重県度会郡南伊勢町棚橋竈",
    "表記": "三重県度会郡南伊勢町棚橋竈",
    "住所": {
      "@type": "住所型",
      "都道府県": "三重県",
      "郡": "度会郡",
      "市区町村": "南伊勢町",
      "町名": "棚橋竈"
    },
    "参照": {
      "@type": "参照型",
      "種別": "メッシュコード",
      "参照先": [
        "http://data.e-stat.go.jp/lod/gridCode/G2051362395",
        "http://data.e-stat.go.jp/lod/gridCode/G2051363304"
      ]
    },
    "画像": [
      "https://cyberjapandata.gsi.go.jp/xyz/std/18/230423/104499.png",
      "https://cyberjapandata.gsi.go.jp/xyz/std/18/230416/104494.png"
    ]
  },
  {
    "@context": "https://geonames.jp/context.jsonld",
    "@id": "https://geonames.jp/resource/三重県度会郡南伊勢町棚橋竈",
    "@type": "Feature",
    "isDefinedBy": "https://indigo-lab.github.io/geonamesjp/三重県/度会郡/南伊勢町/棚橋竈.json",
    "name": "棚橋竈",
    "alternateName": [],
    "parentFeature": "https://geonames.jp/resource/三重県度会郡南伊勢町"
  }
]
