[
  {
    "@context": "https://imi.go.jp/ns/core/context.jsonld",
    "@type": "場所型",
    "@id": "https://geonames.jp/resource/富山県高岡市下麻生",
    "表記": "富山県高岡市下麻生",
    "住所": {
      "@type": "住所型",
      "都道府県": "富山県",
      "市区町村": "高岡市",
      "町名": "下麻生",
      "住所コード": [
        "http://data.e-stat.go.jp/lod/smallArea/g00200521/2015/S162021140",
        "http://data.e-stat.go.jp/lod/smallArea/g00200521/2015/S16202114001"
      ]
    },
    "参照": {
      "@type": "参照型",
      "種別": "メッシュコード",
      "参照先": [
        "http://data.e-stat.go.jp/lod/gridCode/G2055370021",
        "http://data.e-stat.go.jp/lod/gridCode/G2055370020",
        "http://data.e-stat.go.jp/lod/gridCode/G2055370031",
        "http://data.e-stat.go.jp/lod/gridCode/G2055370032",
        "http://data.e-stat.go.jp/lod/gridCode/G2055370030"
      ]
    },
    "画像": [
      "https://cyberjapandata.gsi.go.jp/xyz/std/18/230849/102316.png",
      "https://cyberjapandata.gsi.go.jp/xyz/std/18/230849/102321.png",
      "https://cyberjapandata.gsi.go.jp/xyz/std/18/230848/102321.png",
      "https://cyberjapandata.gsi.go.jp/xyz/std/18/230843/102312.png",
      "https://cyberjapandata.gsi.go.jp/xyz/std/18/230843/102313.png",
      "https://cyberjapandata.gsi.go.jp/xyz/std/18/230843/102314.png",
      "https://cyberjapandata.gsi.go.jp/xyz/std/18/230848/102320.png",
      "https://cyberjapandata.gsi.go.jp/xyz/std/18/230844/102313.png",
      "https://cyberjapandata.gsi.go.jp/xyz/std/18/230845/102313.png",
      "https://cyberjapandata.gsi.go.jp/xyz/std/18/230844/102314.png",
      "https://cyberjapandata.gsi.go.jp/xyz/std/18/230845/102315.png",
      "https://cyberjapandata.gsi.go.jp/xyz/std/18/230846/102313.png",
      "https://cyberjapandata.gsi.go.jp/xyz/std/18/230848/102319.png",
      "https://cyberjapandata.gsi.go.jp/xyz/std/18/230844/102316.png",
      "https://cyberjapandata.gsi.go.jp/xyz/std/18/230845/102317.png",
      "https://cyberjapandata.gsi.go.jp/xyz/std/18/230844/102317.png",
      "https://cyberjapandata.gsi.go.jp/xyz/std/18/230843/102316.png",
      "https://cyberjapandata.gsi.go.jp/xyz/std/18/230842/102315.png",
      "https://cyberjapandata.gsi.go.jp/xyz/std/18/230841/102317.png",
      "https://cyberjapandata.gsi.go.jp/xyz/std/18/230842/102318.png",
      "https://cyberjapandata.gsi.go.jp/xyz/std/18/230841/102319.png",
      "https://cyberjapandata.gsi.go.jp/xyz/std/18/230840/102320.png",
      "https://cyberjapandata.gsi.go.jp/xyz/std/18/230841/102320.png",
      "https://cyberjapandata.gsi.go.jp/xyz/std/18/230843/102318.png",
      "https://cyberjapandata.gsi.go.jp/xyz/std/18/230842/102319.png",
      "https://cyberjapandata.gsi.go.jp/xyz/std/18/230842/102320.png",
      "https://cyberjapandata.gsi.go.jp/xyz/std/18/230843/102320.png",
      "https://cyberjapandata.gsi.go.jp/xyz/std/18/230843/102319.png",
      "https://cyberjapandata.gsi.go.jp/xyz/std/18/230847/102320.png",
      "https://cyberjapandata.gsi.go.jp/xyz/std/18/230844/102318.png",
      "https://cyberjapandata.gsi.go.jp/xyz/std/18/230845/102319.png",
      "https://cyberjapandata.gsi.go.jp/xyz/std/18/230845/102318.png",
      "https://cyberjapandata.gsi.go.jp/xyz/std/18/230846/102318.png",
      "https://cyberjapandata.gsi.go.jp/xyz/std/18/230847/102319.png",
      "https://cyberjapandata.gsi.go.jp/xyz/std/18/230846/102317.png",
      "https://cyberjapandata.gsi.go.jp/xyz/std/18/230847/102317.png",
      "https://cyberjapandata.gsi.go.jp/xyz/std/18/230847/102316.png",
      "https://cyberjapandata.gsi.go.jp/xyz/std/18/230847/102315.png",
      "https://cyberjapandata.gsi.go.jp/xyz/std/18/230846/102316.png",
      "https://cyberjapandata.gsi.go.jp/xyz/std/18/230847/102314.png",
      "https://cyberjapandata.gsi.go.jp/xyz/std/18/230848/102314.png",
      "https://cyberjapandata.gsi.go.jp/xyz/std/18/230849/102313.png",
      "https://cyberjapandata.gsi.go.jp/xyz/std/18/230849/102312.png",
      "https://cyberjapandata.gsi.go.jp/xyz/std/18/230850/102313.png",
      "https://cyberjapandata.gsi.go.jp/xyz/std/18/230851/102313.png",
      "https://cyberjapandata.gsi.go.jp/xyz/std/18/230851/102314.png",
      "https://cyberjapandata.gsi.go.jp/xyz/std/18/230850/102314.png",
      "https://cyberjapandata.gsi.go.jp/xyz/std/18/230849/102314.png",
      "https://cyberjapandata.gsi.go.jp/xyz/std/18/230848/102316.png",
      "https://cyberjapandata.gsi.go.jp/xyz/std/18/230849/102318.png",
      "https://cyberjapandata.gsi.go.jp/xyz/std/18/230848/102318.png",
      "https://cyberjapandata.gsi.go.jp/xyz/std/18/230846/102320.png",
      "https://cyberjapandata.gsi.go.jp/xyz/std/18/230845/102320.png",
      "https://cyberjapandata.gsi.go.jp/xyz/std/18/230839/102317.png",
      "https://cyberjapandata.gsi.go.jp/xyz/std/18/230840/102315.png",
      "https://cyberjapandata.gsi.go.jp/xyz/std/18/230840/102319.png",
      "https://cyberjapandata.gsi.go.jp/xyz/std/18/230842/102312.png",
      "https://cyberjapandata.gsi.go.jp/xyz/std/18/230841/102313.png",
      "https://cyberjapandata.gsi.go.jp/xyz/std/18/230843/102311.png",
      "https://cyberjapandata.gsi.go.jp/xyz/std/18/230842/102311.png",
      "https://cyberjapandata.gsi.go.jp/xyz/std/18/230849/102320.png",
      "https://cyberjapandata.gsi.go.jp/xyz/std/18/230849/102319.png",
      "https://cyberjapandata.gsi.go.jp/xyz/std/18/230850/102315.png",
      "https://cyberjapandata.gsi.go.jp/xyz/std/18/230849/102315.png",
      "https://cyberjapandata.gsi.go.jp/xyz/std/18/230846/102319.png",
      "https://cyberjapandata.gsi.go.jp/xyz/std/18/230844/102320.png",
      "https://cyberjapandata.gsi.go.jp/xyz/std/18/230841/102312.png",
      "https://cyberjapandata.gsi.go.jp/xyz/std/18/230840/102316.png",
      "https://cyberjapandata.gsi.go.jp/xyz/std/18/230841/102314.png",
      "https://cyberjapandata.gsi.go.jp/xyz/std/18/230840/102318.png",
      "https://cyberjapandata.gsi.go.jp/xyz/std/18/230841/102316.png",
      "https://cyberjapandata.gsi.go.jp/xyz/std/18/230844/102319.png",
      "https://cyberjapandata.gsi.go.jp/xyz/std/18/230844/102312.png",
      "https://cyberjapandata.gsi.go.jp/xyz/std/18/230845/102314.png",
      "https://cyberjapandata.gsi.go.jp/xyz/std/18/230847/102321.png",
      "https://cyberjapandata.gsi.go.jp/xyz/std/18/230848/102312.png"
    ]
  },
  {
    "@context": "https://geonames.jp/context.jsonld",
    "@id": "https://geonames.jp/resource/富山県高岡市下麻生",
    "@type": "Feature",
    "isDefinedBy": "https://indigo-lab.github.io/geonamesjp/富山県/高岡市/下麻生.json",
    "name": "下麻生",
    "alternateName": [],
    "parentFeature": "https://geonames.jp/resource/富山県高岡市"
  }
]
