[
  {
    "@context": "https://imi.go.jp/ns/core/context.jsonld",
    "@type": "場所型",
    "@id": "https://geonames.jp/resource/富山県高岡市六家",
    "表記": "富山県高岡市六家",
    "住所": {
      "@type": "住所型",
      "都道府県": "富山県",
      "市区町村": "高岡市",
      "町名": "六家",
      "住所コード": [
        "http://data.e-stat.go.jp/lod/smallArea/g00200521/2015/S162023160"
      ]
    },
    "参照": {
      "@type": "参照型",
      "種別": "メッシュコード",
      "参照先": [
        "http://data.e-stat.go.jp/lod/gridCode/G2055360787",
        "http://data.e-stat.go.jp/lod/gridCode/G2055360777",
        "http://data.e-stat.go.jp/lod/gridCode/G2055360788",
        "http://data.e-stat.go.jp/lod/gridCode/G2055360797"
      ]
    },
    "画像": [
      "https://cyberjapandata.gsi.go.jp/xyz/std/18/230812/102275.png",
      "https://cyberjapandata.gsi.go.jp/xyz/std/18/230812/102273.png",
      "https://cyberjapandata.gsi.go.jp/xyz/std/18/230811/102274.png",
      "https://cyberjapandata.gsi.go.jp/xyz/std/18/230810/102275.png",
      "https://cyberjapandata.gsi.go.jp/xyz/std/18/230811/102275.png",
      "https://cyberjapandata.gsi.go.jp/xyz/std/18/230811/102276.png",
      "https://cyberjapandata.gsi.go.jp/xyz/std/18/230812/102276.png",
      "https://cyberjapandata.gsi.go.jp/xyz/std/18/230812/102274.png",
      "https://cyberjapandata.gsi.go.jp/xyz/std/18/230814/102274.png",
      "https://cyberjapandata.gsi.go.jp/xyz/std/18/230814/102273.png",
      "https://cyberjapandata.gsi.go.jp/xyz/std/18/230813/102275.png",
      "https://cyberjapandata.gsi.go.jp/xyz/std/18/230813/102276.png",
      "https://cyberjapandata.gsi.go.jp/xyz/std/18/230811/102277.png",
      "https://cyberjapandata.gsi.go.jp/xyz/std/18/230810/102277.png",
      "https://cyberjapandata.gsi.go.jp/xyz/std/18/230810/102278.png",
      "https://cyberjapandata.gsi.go.jp/xyz/std/18/230811/102278.png",
      "https://cyberjapandata.gsi.go.jp/xyz/std/18/230815/102272.png",
      "https://cyberjapandata.gsi.go.jp/xyz/std/18/230810/102274.png",
      "https://cyberjapandata.gsi.go.jp/xyz/std/18/230809/102274.png",
      "https://cyberjapandata.gsi.go.jp/xyz/std/18/230814/102275.png",
      "https://cyberjapandata.gsi.go.jp/xyz/std/18/230813/102272.png",
      "https://cyberjapandata.gsi.go.jp/xyz/std/18/230816/102271.png",
      "https://cyberjapandata.gsi.go.jp/xyz/std/18/230811/102269.png",
      "https://cyberjapandata.gsi.go.jp/xyz/std/18/230812/102271.png",
      "https://cyberjapandata.gsi.go.jp/xyz/std/18/230809/102275.png",
      "https://cyberjapandata.gsi.go.jp/xyz/std/18/230812/102277.png",
      "https://cyberjapandata.gsi.go.jp/xyz/std/18/230811/102272.png",
      "https://cyberjapandata.gsi.go.jp/xyz/std/18/230814/102272.png",
      "https://cyberjapandata.gsi.go.jp/xyz/std/18/230813/102277.png",
      "https://cyberjapandata.gsi.go.jp/xyz/std/18/230814/102276.png",
      "https://cyberjapandata.gsi.go.jp/xyz/std/18/230815/102275.png",
      "https://cyberjapandata.gsi.go.jp/xyz/std/18/230816/102272.png"
    ]
  },
  {
    "@context": "https://geonames.jp/context.jsonld",
    "@id": "https://geonames.jp/resource/富山県高岡市六家",
    "@type": "Feature",
    "isDefinedBy": "https://indigo-lab.github.io/geonamesjp/富山県/高岡市/六家.json",
    "name": "六家",
    "alternateName": [],
    "parentFeature": "https://geonames.jp/resource/富山県高岡市"
  }
]
