[
  {
    "@context": "https://imi.go.jp/ns/core/context.jsonld",
    "@type": "場所型",
    "@id": "https://geonames.jp/resource/栃木県小山市塚崎",
    "表記": "栃木県小山市塚崎",
    "住所": {
      "@type": "住所型",
      "都道府県": "栃木県",
      "市区町村": "小山市",
      "町名": "塚崎"
    },
    "参照": {
      "@type": "参照型",
      "種別": "メッシュコード",
      "参照先": [
        "http://data.e-stat.go.jp/lod/gridCode/G2054393605",
        "http://data.e-stat.go.jp/lod/gridCode/G2054393614",
        "http://data.e-stat.go.jp/lod/gridCode/G2054393615",
        "http://data.e-stat.go.jp/lod/gridCode/G2054393624",
        "http://data.e-stat.go.jp/lod/gridCode/G2054393625",
        "http://data.e-stat.go.jp/lod/gridCode/G2054393634",
        "http://data.e-stat.go.jp/lod/gridCode/G2054393644"
      ]
    },
    "画像": [
      "https://cyberjapandata.gsi.go.jp/xyz/std/18/232879/102702.png",
      "https://cyberjapandata.gsi.go.jp/xyz/std/18/232882/102708.png",
      "https://cyberjapandata.gsi.go.jp/xyz/std/18/232883/102707.png",
      "https://cyberjapandata.gsi.go.jp/xyz/std/18/232881/102709.png",
      "https://cyberjapandata.gsi.go.jp/xyz/std/18/232883/102704.png",
      "https://cyberjapandata.gsi.go.jp/xyz/std/18/232880/102705.png",
      "https://cyberjapandata.gsi.go.jp/xyz/std/18/232882/102700.png",
      "https://cyberjapandata.gsi.go.jp/xyz/std/18/232882/102695.png",
      "https://cyberjapandata.gsi.go.jp/xyz/std/18/232884/102698.png",
      "https://cyberjapandata.gsi.go.jp/xyz/std/18/232877/102696.png",
      "https://cyberjapandata.gsi.go.jp/xyz/std/18/232873/102702.png",
      "https://cyberjapandata.gsi.go.jp/xyz/std/18/232872/102696.png",
      "https://cyberjapandata.gsi.go.jp/xyz/std/18/232876/102691.png",
      "https://cyberjapandata.gsi.go.jp/xyz/std/18/232875/102691.png",
      "https://cyberjapandata.gsi.go.jp/xyz/std/18/232874/102690.png",
      "https://cyberjapandata.gsi.go.jp/xyz/std/18/232875/102685.png",
      "https://cyberjapandata.gsi.go.jp/xyz/std/18/232875/102687.png",
      "https://cyberjapandata.gsi.go.jp/xyz/std/18/232875/102686.png",
      "https://cyberjapandata.gsi.go.jp/xyz/std/18/232874/102680.png",
      "https://cyberjapandata.gsi.go.jp/xyz/std/18/232875/102682.png"
    ]
  },
  {
    "@context": "https://geonames.jp/context.jsonld",
    "@id": "https://geonames.jp/resource/栃木県小山市塚崎",
    "@type": "Feature",
    "isDefinedBy": "https://indigo-lab.github.io/geonamesjp/栃木県/小山市/塚崎.json",
    "name": "塚崎",
    "alternateName": [],
    "parentFeature": "https://geonames.jp/resource/栃木県小山市"
  }
]
