[
  {
    "@context": "https://imi.go.jp/ns/core/context.jsonld",
    "@type": "場所型",
    "@id": "https://geonames.jp/resource/佐賀県唐津市浦",
    "表記": "佐賀県唐津市浦",
    "住所": {
      "@type": "住所型",
      "都道府県": "佐賀県",
      "市区町村": "唐津市",
      "町名": "浦",
      "住所コード": [
        "http://data.e-stat.go.jp/lod/smallArea/g00200521/2015/S412020980"
      ]
    },
    "参照": {
      "@type": "参照型",
      "種別": "メッシュコード",
      "参照先": [
        "http://data.e-stat.go.jp/lod/gridCode/G2050291784",
        "http://data.e-stat.go.jp/lod/gridCode/G2050291785",
        "http://data.e-stat.go.jp/lod/gridCode/G2050291794",
        "http://data.e-stat.go.jp/lod/gridCode/G2050291775",
        "http://data.e-stat.go.jp/lod/gridCode/G2050291795"
      ]
    },
    "画像": [
      "https://cyberjapandata.gsi.go.jp/xyz/std/18/225693/105166.png",
      "https://cyberjapandata.gsi.go.jp/xyz/std/18/225691/105166.png",
      "https://cyberjapandata.gsi.go.jp/xyz/std/18/225689/105166.png",
      "https://cyberjapandata.gsi.go.jp/xyz/std/18/225688/105167.png",
      "https://cyberjapandata.gsi.go.jp/xyz/std/18/225687/105161.png",
      "https://cyberjapandata.gsi.go.jp/xyz/std/18/225691/105165.png",
      "https://cyberjapandata.gsi.go.jp/xyz/std/18/225688/105165.png",
      "https://cyberjapandata.gsi.go.jp/xyz/std/18/225689/105167.png",
      "https://cyberjapandata.gsi.go.jp/xyz/std/18/225684/105168.png",
      "https://cyberjapandata.gsi.go.jp/xyz/std/18/225689/105168.png",
      "https://cyberjapandata.gsi.go.jp/xyz/std/18/225687/105167.png",
      "https://cyberjapandata.gsi.go.jp/xyz/std/18/225687/105165.png",
      "https://cyberjapandata.gsi.go.jp/xyz/std/18/225682/105164.png",
      "https://cyberjapandata.gsi.go.jp/xyz/std/18/225687/105164.png",
      "https://cyberjapandata.gsi.go.jp/xyz/std/18/225687/105163.png",
      "https://cyberjapandata.gsi.go.jp/xyz/std/18/225680/105168.png",
      "https://cyberjapandata.gsi.go.jp/xyz/std/18/225689/105169.png",
      "https://cyberjapandata.gsi.go.jp/xyz/std/18/225690/105169.png",
      "https://cyberjapandata.gsi.go.jp/xyz/std/18/225691/105169.png",
      "https://cyberjapandata.gsi.go.jp/xyz/std/18/225691/105167.png",
      "https://cyberjapandata.gsi.go.jp/xyz/std/18/225694/105164.png",
      "https://cyberjapandata.gsi.go.jp/xyz/std/18/225684/105167.png",
      "https://cyberjapandata.gsi.go.jp/xyz/std/18/225687/105166.png",
      "https://cyberjapandata.gsi.go.jp/xyz/std/18/225690/105168.png",
      "https://cyberjapandata.gsi.go.jp/xyz/std/18/225691/105168.png",
      "https://cyberjapandata.gsi.go.jp/xyz/std/18/225693/105167.png",
      "https://cyberjapandata.gsi.go.jp/xyz/std/18/225690/105167.png",
      "https://cyberjapandata.gsi.go.jp/xyz/std/18/225685/105168.png",
      "https://cyberjapandata.gsi.go.jp/xyz/std/18/225687/105170.png",
      "https://cyberjapandata.gsi.go.jp/xyz/std/18/225683/105164.png",
      "https://cyberjapandata.gsi.go.jp/xyz/std/18/225684/105162.png",
      "https://cyberjapandata.gsi.go.jp/xyz/std/18/225683/105167.png",
      "https://cyberjapandata.gsi.go.jp/xyz/std/18/225684/105159.png",
      "https://cyberjapandata.gsi.go.jp/xyz/std/18/225685/105162.png",
      "https://cyberjapandata.gsi.go.jp/xyz/std/18/225687/105169.png",
      "https://cyberjapandata.gsi.go.jp/xyz/std/18/225686/105166.png",
      "https://cyberjapandata.gsi.go.jp/xyz/std/18/225686/105165.png",
      "https://cyberjapandata.gsi.go.jp/xyz/std/18/225688/105162.png",
      "https://cyberjapandata.gsi.go.jp/xyz/std/18/225686/105163.png",
      "https://cyberjapandata.gsi.go.jp/xyz/std/18/225686/105167.png",
      "https://cyberjapandata.gsi.go.jp/xyz/std/18/225688/105168.png",
      "https://cyberjapandata.gsi.go.jp/xyz/std/18/225688/105166.png",
      "https://cyberjapandata.gsi.go.jp/xyz/std/18/225689/105165.png",
      "https://cyberjapandata.gsi.go.jp/xyz/std/18/225691/105161.png",
      "https://cyberjapandata.gsi.go.jp/xyz/std/18/225691/105170.png",
      "https://cyberjapandata.gsi.go.jp/xyz/std/18/225691/105164.png",
      "https://cyberjapandata.gsi.go.jp/xyz/std/18/225694/105165.png",
      "https://cyberjapandata.gsi.go.jp/xyz/std/18/225692/105170.png",
      "https://cyberjapandata.gsi.go.jp/xyz/std/18/225692/105168.png",
      "https://cyberjapandata.gsi.go.jp/xyz/std/18/225693/105164.png",
      "https://cyberjapandata.gsi.go.jp/xyz/std/18/225692/105169.png",
      "https://cyberjapandata.gsi.go.jp/xyz/std/18/225692/105165.png",
      "https://cyberjapandata.gsi.go.jp/xyz/std/18/225693/105170.png",
      "https://cyberjapandata.gsi.go.jp/xyz/std/18/225693/105169.png",
      "https://cyberjapandata.gsi.go.jp/xyz/std/18/225693/105163.png"
    ]
  },
  {
    "@context": "https://geonames.jp/context.jsonld",
    "@id": "https://geonames.jp/resource/佐賀県唐津市浦",
    "@type": "Feature",
    "isDefinedBy": "https://indigo-lab.github.io/geonamesjp/佐賀県/唐津市/浦.json",
    "name": "浦",
    "alternateName": [],
    "parentFeature": "https://geonames.jp/resource/佐賀県唐津市"
  }
]
