[
  {
    "@context": "https://imi.go.jp/ns/core/context.jsonld",
    "@type": "場所型",
    "@id": "https://geonames.jp/resource/北海道札幌市北区新川",
    "表記": "北海道札幌市北区新川",
    "住所": {
      "@type": "住所型",
      "都道府県": "北海道",
      "市区町村": "札幌市",
      "区": "北区",
      "町名": "新川",
      "住所コード": [
        "http://data.e-stat.go.jp/lod/smallArea/g00200521/2015/S011020200"
      ]
    },
    "参照": {
      "@type": "参照型",
      "種別": "メッシュコード",
      "参照先": [
        "http://data.e-stat.go.jp/lod/gridCode/G2064415243",
        "http://data.e-stat.go.jp/lod/gridCode/G2064415234",
        "http://data.e-stat.go.jp/lod/gridCode/G2064415242",
        "http://data.e-stat.go.jp/lod/gridCode/G2064415244",
        "http://data.e-stat.go.jp/lod/gridCode/G2064415252",
        "http://data.e-stat.go.jp/lod/gridCode/G2064415253",
        "http://data.e-stat.go.jp/lod/gridCode/G2064415263",
        "http://data.e-stat.go.jp/lod/gridCode/G2064415233",
        "http://data.e-stat.go.jp/lod/gridCode/G2064415251"
      ]
    },
    "画像": [
      "https://cyberjapandata.gsi.go.jp/xyz/std/18/233959/96204.png",
      "https://cyberjapandata.gsi.go.jp/xyz/std/18/233960/96206.png",
      "https://cyberjapandata.gsi.go.jp/xyz/std/18/233953/96203.png",
      "https://cyberjapandata.gsi.go.jp/xyz/std/18/233946/96198.png",
      "https://cyberjapandata.gsi.go.jp/xyz/std/18/233966/96209.png",
      "https://cyberjapandata.gsi.go.jp/xyz/std/18/233962/96205.png",
      "https://cyberjapandata.gsi.go.jp/xyz/std/18/233960/96204.png",
      "https://cyberjapandata.gsi.go.jp/xyz/std/18/233960/96203.png",
      "https://cyberjapandata.gsi.go.jp/xyz/std/18/233954/96201.png",
      "https://cyberjapandata.gsi.go.jp/xyz/std/18/233954/96200.png",
      "https://cyberjapandata.gsi.go.jp/xyz/std/18/233955/96198.png",
      "https://cyberjapandata.gsi.go.jp/xyz/std/18/233954/96199.png",
      "https://cyberjapandata.gsi.go.jp/xyz/std/18/233963/96205.png",
      "https://cyberjapandata.gsi.go.jp/xyz/std/18/233963/96204.png",
      "https://cyberjapandata.gsi.go.jp/xyz/std/18/233964/96204.png",
      "https://cyberjapandata.gsi.go.jp/xyz/std/18/233963/96203.png",
      "https://cyberjapandata.gsi.go.jp/xyz/std/18/233960/96201.png",
      "https://cyberjapandata.gsi.go.jp/xyz/std/18/233958/96200.png",
      "https://cyberjapandata.gsi.go.jp/xyz/std/18/233952/96195.png",
      "https://cyberjapandata.gsi.go.jp/xyz/std/18/233949/96194.png",
      "https://cyberjapandata.gsi.go.jp/xyz/std/18/233956/96188.png",
      "https://cyberjapandata.gsi.go.jp/xyz/std/18/233958/96205.png",
      "https://cyberjapandata.gsi.go.jp/xyz/std/18/233959/96208.png",
      "https://cyberjapandata.gsi.go.jp/xyz/std/18/233961/96202.png",
      "https://cyberjapandata.gsi.go.jp/xyz/std/18/233959/96203.png",
      "https://cyberjapandata.gsi.go.jp/xyz/std/18/233958/96202.png",
      "https://cyberjapandata.gsi.go.jp/xyz/std/18/233957/96200.png",
      "https://cyberjapandata.gsi.go.jp/xyz/std/18/233945/96193.png",
      "https://cyberjapandata.gsi.go.jp/xyz/std/18/233951/96192.png",
      "https://cyberjapandata.gsi.go.jp/xyz/std/18/233948/96195.png",
      "https://cyberjapandata.gsi.go.jp/xyz/std/18/233962/96204.png",
      "https://cyberjapandata.gsi.go.jp/xyz/std/18/233953/96197.png",
      "https://cyberjapandata.gsi.go.jp/xyz/std/18/233944/96197.png",
      "https://cyberjapandata.gsi.go.jp/xyz/std/18/233946/96199.png",
      "https://cyberjapandata.gsi.go.jp/xyz/std/18/233954/96198.png",
      "https://cyberjapandata.gsi.go.jp/xyz/std/18/233954/96202.png",
      "https://cyberjapandata.gsi.go.jp/xyz/std/18/233959/96206.png",
      "https://cyberjapandata.gsi.go.jp/xyz/std/18/233959/96202.png",
      "https://cyberjapandata.gsi.go.jp/xyz/std/18/233958/96207.png",
      "https://cyberjapandata.gsi.go.jp/xyz/std/18/233959/96201.png",
      "https://cyberjapandata.gsi.go.jp/xyz/std/18/233966/96207.png",
      "https://cyberjapandata.gsi.go.jp/xyz/std/18/233964/96207.png",
      "https://cyberjapandata.gsi.go.jp/xyz/std/18/233945/96192.png"
    ]
  },
  {
    "@context": "https://geonames.jp/context.jsonld",
    "@id": "https://geonames.jp/resource/北海道札幌市北区新川",
    "@type": "Feature",
    "isDefinedBy": "https://indigo-lab.github.io/geonamesjp/北海道/札幌市/北区/新川.json",
    "name": "新川",
    "alternateName": [],
    "parentFeature": "https://geonames.jp/resource/北海道札幌市北区"
  }
]
