[
  {
    "@context": "https://imi.go.jp/ns/core/context.jsonld",
    "@type": "場所型",
    "@id": "https://geonames.jp/resource/三重県上野市比土",
    "表記": "三重県上野市比土",
    "住所": {
      "@type": "住所型",
      "都道府県": "三重県",
      "市区町村": "上野市",
      "町名": "比土"
    },
    "参照": {
      "@type": "参照型",
      "種別": "メッシュコード",
      "参照先": [
        "http://data.e-stat.go.jp/lod/gridCode/G2051367192",
        "http://data.e-stat.go.jp/lod/gridCode/G2052360102",
        "http://data.e-stat.go.jp/lod/gridCode/G2052360112",
        "http://data.e-stat.go.jp/lod/gridCode/G2052360113",
        "http://data.e-stat.go.jp/lod/gridCode/G2052360111"
      ]
    },
    "画像": [
      "https://cyberjapandata.gsi.go.jp/xyz/std/18/230217/104120.png",
      "https://cyberjapandata.gsi.go.jp/xyz/std/18/230220/104122.png",
      "https://cyberjapandata.gsi.go.jp/xyz/std/18/230220/104124.png",
      "https://cyberjapandata.gsi.go.jp/xyz/std/18/230224/104122.png",
      "https://cyberjapandata.gsi.go.jp/xyz/std/18/230221/104121.png",
      "https://cyberjapandata.gsi.go.jp/xyz/std/18/230219/104123.png",
      "https://cyberjapandata.gsi.go.jp/xyz/std/18/230222/104128.png",
      "https://cyberjapandata.gsi.go.jp/xyz/std/18/230218/104123.png",
      "https://cyberjapandata.gsi.go.jp/xyz/std/18/230218/104121.png",
      "https://cyberjapandata.gsi.go.jp/xyz/std/18/230216/104120.png",
      "https://cyberjapandata.gsi.go.jp/xyz/std/18/230218/104122.png",
      "https://cyberjapandata.gsi.go.jp/xyz/std/18/230218/104126.png",
      "https://cyberjapandata.gsi.go.jp/xyz/std/18/230217/104126.png",
      "https://cyberjapandata.gsi.go.jp/xyz/std/18/230218/104127.png",
      "https://cyberjapandata.gsi.go.jp/xyz/std/18/230219/104130.png",
      "https://cyberjapandata.gsi.go.jp/xyz/std/18/230217/104127.png",
      "https://cyberjapandata.gsi.go.jp/xyz/std/18/230216/104134.png",
      "https://cyberjapandata.gsi.go.jp/xyz/std/18/230218/104130.png",
      "https://cyberjapandata.gsi.go.jp/xyz/std/18/230219/104131.png",
      "https://cyberjapandata.gsi.go.jp/xyz/std/18/230216/104124.png",
      "https://cyberjapandata.gsi.go.jp/xyz/std/18/230215/104123.png",
      "https://cyberjapandata.gsi.go.jp/xyz/std/18/230216/104122.png",
      "https://cyberjapandata.gsi.go.jp/xyz/std/18/230216/104121.png",
      "https://cyberjapandata.gsi.go.jp/xyz/std/18/230219/104121.png",
      "https://cyberjapandata.gsi.go.jp/xyz/std/18/230211/104122.png"
    ]
  },
  {
    "@context": "https://geonames.jp/context.jsonld",
    "@id": "https://geonames.jp/resource/三重県上野市比土",
    "@type": "Feature",
    "isDefinedBy": "https://indigo-lab.github.io/geonamesjp/三重県/上野市/比土.json",
    "name": "比土",
    "alternateName": [],
    "parentFeature": "https://geonames.jp/resource/三重県上野市"
  }
]
