[
  {
    "@context": "https://imi.go.jp/ns/core/context.jsonld",
    "@type": "場所型",
    "@id": "https://geonames.jp/resource/山梨県甲府市小瀬町",
    "表記": "山梨県甲府市小瀬町",
    "住所": {
      "@type": "住所型",
      "都道府県": "山梨県",
      "市区町村": "小瀬町",
      "住所コード": [
        "http://data.e-stat.go.jp/lod/smallArea/g00200521/2015/S192010950",
        "http://data.e-stat.go.jp/lod/smallArea/g00200521/2015/S192010940"
      ]
    },
    "参照": {
      "@type": "参照型",
      "種別": "メッシュコード",
      "参照先": [
        "http://data.e-stat.go.jp/lod/gridCode/G2053383446",
        "http://data.e-stat.go.jp/lod/gridCode/G2053383447",
        "http://data.e-stat.go.jp/lod/gridCode/G2053383456",
        "http://data.e-stat.go.jp/lod/gridCode/G2053383457",
        "http://data.e-stat.go.jp/lod/gridCode/G2053383455"
      ]
    },
    "画像": [
      "https://cyberjapandata.gsi.go.jp/xyz/std/18/231981/103274.png",
      "https://cyberjapandata.gsi.go.jp/xyz/std/18/231980/103274.png",
      "https://cyberjapandata.gsi.go.jp/xyz/std/18/231979/103274.png",
      "https://cyberjapandata.gsi.go.jp/xyz/std/18/231980/103273.png",
      "https://cyberjapandata.gsi.go.jp/xyz/std/18/231980/103275.png",
      "https://cyberjapandata.gsi.go.jp/xyz/std/18/231994/103278.png",
      "https://cyberjapandata.gsi.go.jp/xyz/std/18/231986/103277.png",
      "https://cyberjapandata.gsi.go.jp/xyz/std/18/231990/103277.png",
      "https://cyberjapandata.gsi.go.jp/xyz/std/18/231987/103282.png",
      "https://cyberjapandata.gsi.go.jp/xyz/std/18/231981/103273.png",
      "https://cyberjapandata.gsi.go.jp/xyz/std/18/231983/103275.png",
      "https://cyberjapandata.gsi.go.jp/xyz/std/18/231983/103276.png",
      "https://cyberjapandata.gsi.go.jp/xyz/std/18/231984/103275.png",
      "https://cyberjapandata.gsi.go.jp/xyz/std/18/231983/103273.png",
      "https://cyberjapandata.gsi.go.jp/xyz/std/18/231982/103273.png",
      "https://cyberjapandata.gsi.go.jp/xyz/std/18/231985/103274.png",
      "https://cyberjapandata.gsi.go.jp/xyz/std/18/231985/103275.png",
      "https://cyberjapandata.gsi.go.jp/xyz/std/18/231984/103276.png",
      "https://cyberjapandata.gsi.go.jp/xyz/std/18/231984/103278.png",
      "https://cyberjapandata.gsi.go.jp/xyz/std/18/231986/103275.png",
      "https://cyberjapandata.gsi.go.jp/xyz/std/18/231986/103274.png",
      "https://cyberjapandata.gsi.go.jp/xyz/std/18/231988/103274.png",
      "https://cyberjapandata.gsi.go.jp/xyz/std/18/231988/103275.png",
      "https://cyberjapandata.gsi.go.jp/xyz/std/18/231990/103275.png",
      "https://cyberjapandata.gsi.go.jp/xyz/std/18/231992/103276.png",
      "https://cyberjapandata.gsi.go.jp/xyz/std/18/231990/103276.png",
      "https://cyberjapandata.gsi.go.jp/xyz/std/18/231993/103276.png",
      "https://cyberjapandata.gsi.go.jp/xyz/std/18/231993/103277.png",
      "https://cyberjapandata.gsi.go.jp/xyz/std/18/231991/103278.png",
      "https://cyberjapandata.gsi.go.jp/xyz/std/18/231992/103278.png",
      "https://cyberjapandata.gsi.go.jp/xyz/std/18/231992/103277.png",
      "https://cyberjapandata.gsi.go.jp/xyz/std/18/231992/103279.png",
      "https://cyberjapandata.gsi.go.jp/xyz/std/18/231983/103274.png",
      "https://cyberjapandata.gsi.go.jp/xyz/std/18/231991/103277.png",
      "https://cyberjapandata.gsi.go.jp/xyz/std/18/231991/103279.png",
      "https://cyberjapandata.gsi.go.jp/xyz/std/18/231987/103276.png",
      "https://cyberjapandata.gsi.go.jp/xyz/std/18/231978/103274.png",
      "https://cyberjapandata.gsi.go.jp/xyz/std/18/231979/103273.png",
      "https://cyberjapandata.gsi.go.jp/xyz/std/18/231981/103275.png",
      "https://cyberjapandata.gsi.go.jp/xyz/std/18/231982/103274.png",
      "https://cyberjapandata.gsi.go.jp/xyz/std/18/231982/103275.png",
      "https://cyberjapandata.gsi.go.jp/xyz/std/18/231984/103277.png",
      "https://cyberjapandata.gsi.go.jp/xyz/std/18/231984/103274.png",
      "https://cyberjapandata.gsi.go.jp/xyz/std/18/231985/103277.png",
      "https://cyberjapandata.gsi.go.jp/xyz/std/18/231985/103276.png",
      "https://cyberjapandata.gsi.go.jp/xyz/std/18/231986/103276.png",
      "https://cyberjapandata.gsi.go.jp/xyz/std/18/231986/103278.png",
      "https://cyberjapandata.gsi.go.jp/xyz/std/18/231987/103277.png",
      "https://cyberjapandata.gsi.go.jp/xyz/std/18/231988/103277.png",
      "https://cyberjapandata.gsi.go.jp/xyz/std/18/231988/103278.png",
      "https://cyberjapandata.gsi.go.jp/xyz/std/18/231988/103276.png",
      "https://cyberjapandata.gsi.go.jp/xyz/std/18/231989/103278.png",
      "https://cyberjapandata.gsi.go.jp/xyz/std/18/231989/103277.png",
      "https://cyberjapandata.gsi.go.jp/xyz/std/18/231989/103279.png",
      "https://cyberjapandata.gsi.go.jp/xyz/std/18/231989/103276.png",
      "https://cyberjapandata.gsi.go.jp/xyz/std/18/231990/103278.png",
      "https://cyberjapandata.gsi.go.jp/xyz/std/18/231989/103280.png",
      "https://cyberjapandata.gsi.go.jp/xyz/std/18/231979/103275.png",
      "https://cyberjapandata.gsi.go.jp/xyz/std/18/231981/103272.png"
    ]
  },
  {
    "@context": "https://geonames.jp/context.jsonld",
    "@id": "https://geonames.jp/resource/山梨県甲府市小瀬町",
    "@type": "Feature",
    "isDefinedBy": "https://indigo-lab.github.io/geonamesjp/山梨県/甲府市/小瀬町.json",
    "name": "小瀬町",
    "alternateName": [],
    "parentFeature": "https://geonames.jp/resource/山梨県甲府市"
  }
]
