[
  {
    "@context": "https://imi.go.jp/ns/core/context.jsonld",
    "@type": "場所型",
    "@id": "https://geonames.jp/resource/愛知県豊田市上渡合町",
    "表記": "愛知県豊田市上渡合町",
    "住所": {
      "@type": "住所型",
      "都道府県": "愛知県",
      "市区町村": "上渡合町",
      "住所コード": [
        "http://data.e-stat.go.jp/lod/smallArea/g00200521/2015/S232112840"
      ]
    },
    "参照": {
      "@type": "参照型",
      "種別": "メッシュコード",
      "参照先": [
        "http://data.e-stat.go.jp/lod/gridCode/G2052376156",
        "http://data.e-stat.go.jp/lod/gridCode/G2052376146",
        "http://data.e-stat.go.jp/lod/gridCode/G2052376155",
        "http://data.e-stat.go.jp/lod/gridCode/G2052376166",
        "http://data.e-stat.go.jp/lod/gridCode/G2052376167"
      ]
    },
    "画像": [
      "https://cyberjapandata.gsi.go.jp/xyz/std/18/230980/103645.png",
      "https://cyberjapandata.gsi.go.jp/xyz/std/18/230981/103650.png",
      "https://cyberjapandata.gsi.go.jp/xyz/std/18/230980/103647.png",
      "https://cyberjapandata.gsi.go.jp/xyz/std/18/230981/103645.png",
      "https://cyberjapandata.gsi.go.jp/xyz/std/18/230979/103644.png",
      "https://cyberjapandata.gsi.go.jp/xyz/std/18/230982/103651.png",
      "https://cyberjapandata.gsi.go.jp/xyz/std/18/230980/103642.png",
      "https://cyberjapandata.gsi.go.jp/xyz/std/18/230978/103644.png",
      "https://cyberjapandata.gsi.go.jp/xyz/std/18/230982/103649.png",
      "https://cyberjapandata.gsi.go.jp/xyz/std/18/230979/103649.png",
      "https://cyberjapandata.gsi.go.jp/xyz/std/18/230980/103643.png",
      "https://cyberjapandata.gsi.go.jp/xyz/std/18/230981/103648.png",
      "https://cyberjapandata.gsi.go.jp/xyz/std/18/230981/103647.png",
      "https://cyberjapandata.gsi.go.jp/xyz/std/18/230979/103646.png",
      "https://cyberjapandata.gsi.go.jp/xyz/std/18/230982/103646.png",
      "https://cyberjapandata.gsi.go.jp/xyz/std/18/230981/103646.png",
      "https://cyberjapandata.gsi.go.jp/xyz/std/18/230979/103645.png",
      "https://cyberjapandata.gsi.go.jp/xyz/std/18/230981/103644.png",
      "https://cyberjapandata.gsi.go.jp/xyz/std/18/230982/103645.png",
      "https://cyberjapandata.gsi.go.jp/xyz/std/18/230983/103641.png",
      "https://cyberjapandata.gsi.go.jp/xyz/std/18/230980/103640.png",
      "https://cyberjapandata.gsi.go.jp/xyz/std/18/230981/103640.png",
      "https://cyberjapandata.gsi.go.jp/xyz/std/18/230980/103641.png",
      "https://cyberjapandata.gsi.go.jp/xyz/std/18/230978/103645.png",
      "https://cyberjapandata.gsi.go.jp/xyz/std/18/230977/103646.png",
      "https://cyberjapandata.gsi.go.jp/xyz/std/18/230980/103646.png",
      "https://cyberjapandata.gsi.go.jp/xyz/std/18/230988/103641.png",
      "https://cyberjapandata.gsi.go.jp/xyz/std/18/230984/103641.png",
      "https://cyberjapandata.gsi.go.jp/xyz/std/18/230980/103639.png",
      "https://cyberjapandata.gsi.go.jp/xyz/std/18/230979/103641.png",
      "https://cyberjapandata.gsi.go.jp/xyz/std/18/230982/103644.png",
      "https://cyberjapandata.gsi.go.jp/xyz/std/18/230983/103646.png",
      "https://cyberjapandata.gsi.go.jp/xyz/std/18/230979/103643.png",
      "https://cyberjapandata.gsi.go.jp/xyz/std/18/230978/103642.png",
      "https://cyberjapandata.gsi.go.jp/xyz/std/18/230979/103648.png",
      "https://cyberjapandata.gsi.go.jp/xyz/std/18/230981/103649.png"
    ]
  },
  {
    "@context": "https://geonames.jp/context.jsonld",
    "@id": "https://geonames.jp/resource/愛知県豊田市上渡合町",
    "@type": "Feature",
    "isDefinedBy": "https://indigo-lab.github.io/geonamesjp/愛知県/豊田市/上渡合町.json",
    "name": "上渡合町",
    "alternateName": [],
    "parentFeature": "https://geonames.jp/resource/愛知県豊田市"
  }
]
