[
  {
    "@context": "https://imi.go.jp/ns/core/context.jsonld",
    "@type": "場所型",
    "@id": "https://geonames.jp/resource/岩手県奥州市江刺区伊手字御堂",
    "表記": "岩手県奥州市江刺区伊手字御堂",
    "住所": {
      "@type": "住所型",
      "都道府県": "岩手県",
      "市区町村": "奥州市",
      "町名": "江刺区伊手字御堂"
    },
    "参照": {
      "@type": "参照型",
      "種別": "メッシュコード",
      "参照先": [
        "http://data.e-stat.go.jp/lod/gridCode/G2058416202"
      ]
    },
    "画像": [
      "https://cyberjapandata.gsi.go.jp/xyz/std/18/233946/100023.png"
    ]
  },
  {
    "@context": "https://geonames.jp/context.jsonld",
    "@id": "https://geonames.jp/resource/岩手県奥州市江刺区伊手字御堂",
    "@type": "Feature",
    "isDefinedBy": "https://indigo-lab.github.io/geonamesjp/岩手県/奥州市/江刺区伊手字御堂.json",
    "name": "江刺区伊手字御堂",
    "alternateName": [],
    "parentFeature": "https://geonames.jp/resource/岩手県奥州市"
  }
]
