[
  {
    "@context": "https://imi.go.jp/ns/core/context.jsonld",
    "@type": "場所型",
    "@id": "https://geonames.jp/resource/栃木県宇都宮市白沢",
    "表記": "栃木県宇都宮市白沢",
    "住所": {
      "@type": "住所型",
      "都道府県": "栃木県",
      "市区町村": "宇都宮市",
      "町名": "白沢"
    },
    "参照": {
      "@type": "参照型",
      "種別": "メッシュコード",
      "参照先": [
        "http://data.e-stat.go.jp/lod/gridCode/G2054397734",
        "http://data.e-stat.go.jp/lod/gridCode/G2054397744",
        "http://data.e-stat.go.jp/lod/gridCode/G2054397745",
        "http://data.e-stat.go.jp/lod/gridCode/G2054397755",
        "http://data.e-stat.go.jp/lod/gridCode/G2054397765",
        "http://data.e-stat.go.jp/lod/gridCode/G2054397766",
        "http://data.e-stat.go.jp/lod/gridCode/G2054397775"
      ]
    },
    "画像": [
      "https://cyberjapandata.gsi.go.jp/xyz/std/18/232971/102375.png",
      "https://cyberjapandata.gsi.go.jp/xyz/std/18/232968/102379.png",
      "https://cyberjapandata.gsi.go.jp/xyz/std/18/232974/102373.png",
      "https://cyberjapandata.gsi.go.jp/xyz/std/18/232975/102369.png",
      "https://cyberjapandata.gsi.go.jp/xyz/std/18/232981/102364.png",
      "https://cyberjapandata.gsi.go.jp/xyz/std/18/232974/102358.png",
      "https://cyberjapandata.gsi.go.jp/xyz/std/18/232971/102367.png",
      "https://cyberjapandata.gsi.go.jp/xyz/std/18/232973/102367.png",
      "https://cyberjapandata.gsi.go.jp/xyz/std/18/232972/102365.png",
      "https://cyberjapandata.gsi.go.jp/xyz/std/18/232975/102367.png",
      "https://cyberjapandata.gsi.go.jp/xyz/std/18/232965/102383.png"
    ]
  },
  {
    "@context": "https://geonames.jp/context.jsonld",
    "@id": "https://geonames.jp/resource/栃木県宇都宮市白沢",
    "@type": "Feature",
    "isDefinedBy": "https://indigo-lab.github.io/geonamesjp/栃木県/宇都宮市/白沢.json",
    "name": "白沢",
    "alternateName": [],
    "parentFeature": "https://geonames.jp/resource/栃木県宇都宮市"
  }
]
