[
  {
    "@context": "https://imi.go.jp/ns/core/context.jsonld",
    "@type": "場所型",
    "@id": "https://geonames.jp/resource/新潟県新潟市女池上山",
    "表記": "新潟県新潟市女池上山",
    "住所": {
      "@type": "住所型",
      "都道府県": "新潟県",
      "市区町村": "新潟市",
      "町名": "女池上山"
    }
  },
  {
    "@context": "https://geonames.jp/context.jsonld",
    "@id": "https://geonames.jp/resource/新潟県新潟市女池上山",
    "@type": "Feature",
    "isDefinedBy": "https://indigo-lab.github.io/geonamesjp/新潟県/新潟市/女池上山.json",
    "name": "女池上山",
    "alternateName": [],
    "parentFeature": "https://geonames.jp/resource/新潟県新潟市",
    "children": [
      "https://geonames.jp/resource/新潟県新潟市女池上山一丁目",
      "https://geonames.jp/resource/新潟県新潟市女池上山二丁目",
      "https://geonames.jp/resource/新潟県新潟市女池上山三丁目",
      "https://geonames.jp/resource/新潟県新潟市女池上山四丁目",
      "https://geonames.jp/resource/新潟県新潟市女池上山五丁目"
    ]
  }
]
